pycolordetector/__init__.py
pycolordetector/pycolordetector.py
pycolordetector-0.0.2.dist-info/LICENSE
pycolordetector-0.0.2.dist-info/METADATA
pycolordetector-0.0.2.dist-info/WHEEL
pycolordetector-0.0.2.dist-info/top_level.txt
pycolordetector-0.0.2.dist-info/RECORD
