Metadata-Version: 2.1
Name: pycolordetector
Version: 0.0.2
Summary: A simple Python package for detecting colors in images
Home-page: https://github.com/sunnysinghnitb/pycolordetector
Author: Sunny Singh
Author-email: sunnysinghnitb@gmail.com
License: MIT
Download-URL: https://pypi.python.org/pypi/pycolordetector
Project-URL: Bug Tracker, https://github.com/sunnysinghnitb/pycolordetector/issues
Project-URL: Documentation, https://pycolordetector.readthedocs.io/en/latest/
Platform: UNKNOWN
Classifier: Programming Language :: Python :: 3
Classifier: License :: OSI Approved :: MIT License
Classifier: Operating System :: OS Independent
